komminarlabs_influxdb3/__init__.py
komminarlabs_influxdb3/_inputs.py
komminarlabs_influxdb3/_utilities.py
komminarlabs_influxdb3/database.py
komminarlabs_influxdb3/get_database.py
komminarlabs_influxdb3/get_databases.py
komminarlabs_influxdb3/get_token.py
komminarlabs_influxdb3/get_tokens.py
komminarlabs_influxdb3/outputs.py
komminarlabs_influxdb3/provider.py
komminarlabs_influxdb3/pulumi-plugin.json
komminarlabs_influxdb3/py.typed
komminarlabs_influxdb3/token.py
komminarlabs_influxdb3/config/__init__.py
komminarlabs_influxdb3/config/__init__.pyi
komminarlabs_influxdb3/config/vars.py
komminarlabs_influxdb3-1.3.0.dist-info/METADATA
komminarlabs_influxdb3-1.3.0.dist-info/WHEEL
komminarlabs_influxdb3-1.3.0.dist-info/top_level.txt
komminarlabs_influxdb3-1.3.0.dist-info/RECORD
